tflocalpattern/__init__.py
tflocalpattern/layers.py
tflocalpattern-0.0.1.dist-info/LICENSE
tflocalpattern-0.0.1.dist-info/METADATA
tflocalpattern-0.0.1.dist-info/WHEEL
tflocalpattern-0.0.1.dist-info/top_level.txt
tflocalpattern-0.0.1.dist-info/RECORD
